MANIFEST.in
README.md
setup.py
pydwm/__init__.py
pydwm.egg-info/PKG-INFO
pydwm.egg-info/SOURCES.txt
pydwm.egg-info/dependency_links.txt
pydwm.egg-info/entry_points.txt
pydwm.egg-info/top_level.txt