Metadata-Version: 1.1
Name: pydwm
Version: 0.1.4
Summary: A simple python wrapper around DWM.
Home-page: https://github.com/benwah/pydwm
Author: Benoit C. Sirois
Author-email: benoitcsirois@gmail.com
License: MIT License
Platform: UNKNOWN
Classifier: Development Status :: 4 - Beta
Classifier: Environment :: X11 Applications
Classifier: Intended Audience :: Developers
Classifier: Intended Audience :: End Users/Desktop
Classifier: License :: OSI Approved :: MIT License
Classifier: Operating System :: POSIX
Classifier: Programming Language :: Python :: 2.7
Classifier: Programming Language :: Python :: 3
Classifier: Programming Language :: Python :: Implementation :: CPython
Classifier: Topic :: Desktop Environment :: Window Managers
